deepchar/__init__.py
deepchar-0.1.dist-info/LICENCE
deepchar-0.1.dist-info/METADATA
deepchar-0.1.dist-info/WHEEL
deepchar-0.1.dist-info/top_level.txt
deepchar-0.1.dist-info/RECORD
