Metadata-Version: 2.1
Name: deepchar
Version: 0.1
Summary: Transliteration with sequence-to-sequence models and transfer learning
Home-page: https://github.com/deepchar/deepchar
Author: ModelFront
Author-email: deepchar@modelfront.com
License: MIT
Download-URL: https://github.com/deepchar/deepchar/archive/0.1.tar.gz
Keywords: natural language processing,text,translation,transliteration,translit
Platform: UNKNOWN
Classifier: Development Status :: 3 - Alpha
Classifier: Intended Audience :: Developers
Classifier: License :: OSI Approved :: MIT License
Classifier: Programming Language :: Python :: 3.3
Classifier: Programming Language :: Python :: 3.4
Classifier: Programming Language :: Python :: 3.5
